.gitignore
MANIFEST.in
Notes.org
README.rst
bootstrap.py
buildout.cfg
pre-commit-check.sh
setup.py
collective/__init__.py
collective.listusers.egg-info/PKG-INFO
collective.listusers.egg-info/SOURCES.txt
collective.listusers.egg-info/dependency_links.txt
collective.listusers.egg-info/entry_points.txt
collective.listusers.egg-info/namespace_packages.txt
collective.listusers.egg-info/not-zip-safe
collective.listusers.egg-info/requires.txt
collective.listusers.egg-info/top_level.txt
collective/listusers/__init__.py
collective/listusers/config.py
collective/listusers/configure.zcml
collective/listusers/controlpanel.py
collective/listusers/interfaces.py
collective/listusers/vocabularies.py
collective/listusers/browser/__init__.py
collective/listusers/browser/configure.zcml
collective/listusers/browser/detailsldapusers.pt
collective/listusers/browser/listldapusers.pt
collective/listusers/browser/listusers.pt
collective/listusers/browser/listusers.py
collective/listusers/browser/vcard.py
collective/listusers/browser/resources/listusers.css
collective/listusers/browser/resources/listusers.js
collective/listusers/browser/resources/print.css
collective/listusers/locales/collective.listusers.pot
collective/listusers/locales/de/LC_MESSAGES/collective.listusers.po
collective/listusers/locales/sl/LC_MESSAGES/collective.listusers.po
collective/listusers/profiles/default/browserlayer.xml
collective/listusers/profiles/default/controlpanel.xml
collective/listusers/profiles/default/metadata.xml
collective/listusers/profiles/default/registry.xml
collective/listusers/tests/__init__.py
collective/listusers/tests/base.py
collective/listusers/tests/test_listusers.py
collective/listusers/tests/test_setup.py
collective/listusers/tests/test_vocabulary.py
docs/CREDITS.rst
docs/HISTORY.rst
docs/LICENSE.rst
docs/README.rst
docs/api.rst
docs/conf.py
docs/customization.rst
docs/index.rst
docs/translations.rst