Metadata-Version: 1.0
Name: collective.listusers
Version: 1.3
Summary: A search form for listing users.
Home-page: https://github.com/collective/collective.listusers
Author: NiteoWeb Ltd.
Author-email: info@niteoweb.com
License: BSD
Keywords: plone search users group LDAP
Platform: UNKNOWN
Classifier: Programming Language :: Python
Classifier: Programming Language :: JavaScript
Classifier: Framework :: Plone
Classifier: License :: OSI Approved :: GNU General Public License (GPL)
